litprog/__init__.py
litprog/__main__.py
litprog/build.py
litprog/capture_cache.py
litprog/cli.py
litprog/common_types.py
litprog/config.py
litprog/gen_docs.py
litprog/html2pdf.py
litprog/html_postproc.py
litprog/index.py
litprog/md2html.py
litprog/package_data.py
litprog/parse.py
litprog/pdf_booklet.py
litprog/pdf_booklet_old.py
litprog/pdf_util.py
litprog/session.py
litprog/simple_cache.py
litprog/utils.py
litprog/vcs.py
litprog/vcs_timeline.py
litprog/watch.py
litprog/static/app.js
litprog/static/check_reloaded.js
litprog/static/codehilite.css
litprog/static/danger.svg
litprog/static/fonts_print.css
litprog/static/fonts_screen.css
litprog/static/general.css
litprog/static/general_v2.css
litprog/static/icon.svg
litprog/static/icon_192.png
litprog/static/info.svg
litprog/static/instapage.js
litprog/static/katex.css
litprog/static/light-grey-terrazzo.png
litprog/static/litprog-docs-badge.svg
litprog/static/navigation.css
litprog/static/navigation.js
litprog/static/pdf_modal.css
litprog/static/popper.js
litprog/static/popper.min.js
litprog/static/print.css
litprog/static/print_a4.css
litprog/static/print_a5.css
litprog/static/print_ereader.css
litprog/static/print_halfletter.css
litprog/static/print_letter.css
litprog/static/print_tallcol.css
litprog/static/print_tallcol_a4.css
litprog/static/print_tallcol_letter.css
litprog/static/screen.css
litprog/static/screen_v2.css
litprog/static/screen_v3.css
litprog/static/slideout.js
litprog/static/template.html
litprog/static/template_v2.html
litprog/static/warn.svg
litprog/static/fonts/bitter-v17-latin-ext_latin-300.ttf
litprog/static/fonts/bitter-v17-latin-ext_latin-300.woff
litprog/static/fonts/bitter-v17-latin-ext_latin-300.woff2
litprog/static/fonts/bitter-v17-latin-ext_latin-600.ttf
litprog/static/fonts/bitter-v17-latin-ext_latin-600.woff
litprog/static/fonts/bitter-v17-latin-ext_latin-600.woff2
litprog/static/fonts/bitter-v17-latin-ext_latin-italic.ttf
litprog/static/fonts/bitter-v17-latin-ext_latin-italic.woff
litprog-2022.1008a0.dist-info/LICENSE
litprog-2022.1008a0.dist-info/METADATA
litprog-2022.1008a0.dist-info/WHEEL
litprog-2022.1008a0.dist-info/entry_points.txt
litprog-2022.1008a0.dist-info/top_level.txt
litprog-2022.1008a0.dist-info/zip-safe
litprog-2022.1008a0.dist-info/RECORD
