Metadata-Version: 2.1
Name: litprog
Version: 2022.1008a0
Summary: Literate Programming using Markdown.
Home-page: https://github.com/litprog/litprog
Author: Manuel Barkhau
Author-email: mbarkhau@gmail.com
License: MIT
Keywords: literate programming markdown litprog
Platform: UNKNOWN
Classifier: Development Status :: 3 - Alpha
Classifier: Environment :: Console
Classifier: Environment :: Other Environment
Classifier: Intended Audience :: Developers
Classifier: License :: OSI Approved :: MIT License
Classifier: Operating System :: Unix
Classifier: Operating System :: POSIX
Classifier: Operating System :: MacOS :: MacOS X
Classifier: Operating System :: Microsoft :: Windows
Classifier: Programming Language :: Python :: 3
Classifier: Programming Language :: Python :: Implementation :: CPython
Classifier: Topic :: Software Development :: Libraries
Classifier: Topic :: Software Development :: Libraries :: Python Modules
Requires-Python: >=3.7
License-File: LICENSE
Requires-Dist: toml
Requires-Dist: PyYAML
Requires-Dist: click (<8.0) ; python_version < "3.6"
Requires-Dist: importlib-resources ; python_version <= "3.8"
Requires-Dist: click ; python_version >= "3.6"
Provides-Extra: html
Requires-Dist: Markdown (>=3.0) ; extra == 'html'
Requires-Dist: markdown-svgbob ; extra == 'html'
Requires-Dist: markdown-aafigure ; extra == 'html'
Requires-Dist: markdown-blockdiag ; extra == 'html'
Requires-Dist: markdown-katex ; extra == 'html'
Requires-Dist: Pygments ; extra == 'html'
Requires-Dist: beautifulsoup4 ; extra == 'html'
Requires-Dist: Jinja2 ; extra == 'html'
Provides-Extra: pdf
Requires-Dist: Markdown (>=3.0) ; extra == 'pdf'
Requires-Dist: markdown-svgbob ; extra == 'pdf'
Requires-Dist: markdown-aafigure ; extra == 'pdf'
Requires-Dist: markdown-blockdiag ; extra == 'pdf'
Requires-Dist: markdown-katex ; extra == 'pdf'
Requires-Dist: Pygments ; extra == 'pdf'
Requires-Dist: beautifulsoup4 ; extra == 'pdf'
Requires-Dist: Jinja2 ; extra == 'pdf'
Requires-Dist: CairoSVG (>=2.5.2) ; extra == 'pdf'
Requires-Dist: WeasyPrint ; extra == 'pdf'
Requires-Dist: Pyphen ; extra == 'pdf'
Requires-Dist: pdfrw ; extra == 'pdf'
Requires-Dist: PyPDF2 ; extra == 'pdf'
